corelp/__init__.py
corelp/icon_pythonLP.png
corelp/modules/Path_LP/Path.py
corelp/modules/Path_LP/__init__.py
corelp/modules/Path_LP/_functions/__init__.py
corelp/modules/Path_LP/_functions/__template__.py
corelp/modules/Path_LP/test_Path.py
corelp/modules/__init__.py
corelp/modules/debug_LP/__init__.py
corelp/modules/debug_LP/_functions/__init__.py
corelp/modules/debug_LP/_functions/__template__.py
corelp/modules/debug_LP/debug.py
corelp/modules/debug_LP/test_debug.py
corelp/modules/folder_LP/__init__.py
corelp/modules/folder_LP/_functions/__init__.py
corelp/modules/folder_LP/_functions/__template__.py
corelp/modules/folder_LP/folder.py
corelp/modules/folder_LP/test_folder.py
corelp/modules/getmodule_LP/__init__.py
corelp/modules/getmodule_LP/_functions/__init__.py
corelp/modules/getmodule_LP/_functions/__template__.py
corelp/modules/getmodule_LP/getmodule.py
corelp/modules/icon_LP/__init__.py
corelp/modules/icon_LP/_functions/__init__.py
corelp/modules/icon_LP/_functions/__template__.py
corelp/modules/icon_LP/icon.py
corelp/modules/icon_LP/test_icon.py
corelp/modules/kwargsself_LP/__init__.py
corelp/modules/kwargsself_LP/_functions/__init__.py
corelp/modules/kwargsself_LP/_functions/__template__.py
corelp/modules/kwargsself_LP/kwargsself.py
corelp/modules/kwargsself_LP/test_kwargsself.py
corelp/modules/prop_LP/__init__.py
corelp/modules/prop_LP/_functions/__init__.py
corelp/modules/prop_LP/_functions/__template__.py
corelp/modules/prop_LP/prop.py
corelp/modules/prop_LP/test_prop.py
corelp/modules/rfrom_LP/__init__.py
corelp/modules/rfrom_LP/_functions/__init__.py
corelp/modules/rfrom_LP/_functions/__template__.py
corelp/modules/rfrom_LP/rfrom.py
corelp/modules/rfrom_LP/test_rfrom.py
corelp/modules/selfkwargs_LP/__init__.py
corelp/modules/selfkwargs_LP/_functions/__init__.py
corelp/modules/selfkwargs_LP/_functions/__template__.py
corelp/modules/selfkwargs_LP/selfkwargs.py
corelp/modules/selfkwargs_LP/test_selfkwargs.py
corelp/modules/test_LP/__init__.py
corelp-1.0.47.dist-info/WHEEL
corelp-1.0.47.dist-info/METADATA
corelp-1.0.47.dist-info/RECORD
