Metadata-Version: 2.3
Name: corelp
Version: 1.0.47
Summary: A library that gathers core functions for python programming.
Requires-Python: >=3.12
